reaver/__init__.py
reaver/run.py
reaver/agents/__init__.py
reaver/agents/a2c.py
reaver/agents/ppo.py
reaver/agents/random.py
reaver/agents/base/__init__.py
reaver/agents/base/actor_critic.py
reaver/agents/base/memory.py
reaver/agents/base/running.py
reaver/configs/atari/base.gin
reaver/configs/gym/CartPole-v0.gin
reaver/configs/gym/base.gin
reaver/configs/gym/continuous.gin
reaver/configs/mujoco/base.gin
reaver/configs/sc2/FindAndDefeatZerglings.gin
reaver/configs/sc2/MoveToBeacon.gin
reaver/configs/sc2/base.gin
reaver/envs/__init__.py
reaver/envs/atari.py
reaver/envs/gym.py
reaver/envs/sc2.py
reaver/envs/base/__init__.py
reaver/envs/base/abc.py
reaver/envs/base/msg_multiproc.py
reaver/envs/base/shm_multiproc.py
reaver/envs/base/spec.py
reaver/models/__init__.py
reaver/models/base/__init__.py
reaver/models/base/cnn.py
reaver/models/base/layers.py
reaver/models/base/mlp.py
reaver/models/base/policy.py
reaver/models/sc2/__init__.py
reaver/models/sc2/fully_conv.py
reaver/models/sc2/policy.py
reaver/utils/__init__.py
reaver/utils/config.py
reaver/utils/experiment.py
reaver/utils/logger.py
reaver/utils/plot.py
reaver/utils/tensorflow.py
reaver/utils/typing.py
reaver-2.1.9.dist-info/LICENSE
reaver-2.1.9.dist-info/METADATA
reaver-2.1.9.dist-info/WHEEL
reaver-2.1.9.dist-info/top_level.txt
reaver-2.1.9.dist-info/RECORD
